codefest/cf04/hdl/mac_correct.v
// mac_correct.v — corrected synthesizable SystemVerilog MAC unit
// Fixes applied vs mac_llm_B.v:
//   1. always_ff instead of always @(posedge clk)
//   2. signed qualifier on all ports and intermediate wire
//   3. logic instead of reg/wire

module mac (
    input  logic        clk,
    input  logic        rst,
    input  logic signed [7:0]  a,
    input  logic signed [7:0]  b,
    output logic signed [31:0] out
);
    logic signed [15:0] product;

    always_comb product = a * b;

    always_ff @(posedge clk) begin
        if (rst)
            out <= 32'sd0;
        else
            out <= out + {{16{product[15]}}, product};
    end
endmodule

codefest/cf04/hdl/mac_tb.v
`timescale 1ns/1ps
module mac_tb;
    logic       clk, rst;
    logic signed [7:0]  a, b;
    logic signed [31:0] out;

    mac dut (.clk(clk), .rst(rst), .a(a), .b(b), .out(out));

    initial clk = 0;
    always #5 clk = ~clk;

    integer fail = 0;

    task check;
        input signed [31:0] expected;
        input [127:0] label;
        begin
            if (out !== expected) begin
                $display("FAIL [%0s]: got %0d, expected %0d", label, out, expected);
                fail = fail + 1;
            end else
                $display("PASS [%0s]: out = %0d", label, out);
        end
    endtask

    initial begin
        $dumpfile("mac_tb.vcd");
        $dumpvars(0, mac_tb);

        // Reset for one cycle
        rst = 1; a = 0; b = 0;
        @(posedge clk); #1;

        // a=3, b=4 for 3 cycles
        rst = 0; a = 8'sd3; b = 8'sd4;
        @(posedge clk); #1; check(32'sd12,  "a=3,b=4 cyc1");
        @(posedge clk); #1; check(32'sd24,  "a=3,b=4 cyc2");
        @(posedge clk); #1; check(32'sd36,  "a=3,b=4 cyc3");

        // Synchronous reset
        rst = 1;
        @(posedge clk); #1; check(32'sd0, "rst");

        // a=-5, b=2 for 2 cycles
        rst = 0; a = -8'sd5; b = 8'sd2;
        @(posedge clk); #1; check(-32'sd10, "a=-5,b=2 cyc1");
        @(posedge clk); #1; check(-32'sd20, "a=-5,b=2 cyc2");

        if (fail == 0)
            $display("ALL TESTS PASSED");
        else
            $display("%0d TEST(S) FAILED", fail);

        $finish;
    end
endmodule

codefest/cf04/cocotb_mac/mac_tb.vcd
$date
	Fri Apr 24 14:45:00 2026
$end
$version
	Icarus Verilog
$end
$timescale
	1ps
$end
$scope module mac_tb $end
$var wire 32 ! out [31:0] $end
$var reg 8 " a [7:0] $end
$var reg 8 # b [7:0] $end
$var reg 1 $ clk $end
$var reg 1 % rst $end
$var integer 32 & fail [31:0] $end
$scope module dut $end
$var wire 8 ' a [7:0] $end
$var wire 8 ( b [7:0] $end
$var wire 1 $ clk $end
$var wire 1 % rst $end
$var reg 32 ) out [31:0] $end
$var reg 16 * product [15:0] $end
$upscope $end
$scope task check $end
$var reg 32 + expected [31:0] $end
$var reg 128 , label [127:0] $end
$upscope $end
$upscope $end
$enddefinitions $end
$comment Show the parameter values. $end
$dumpall
$end
#0
$dumpvars
bx ,
bx +
b0 *
bx )
b0 (
b0 '
b0 &
1%
0$
b0 #
b0 "
bx !
$end
#5000
b0 !
b0 )
1$
#6000
b1100 *
b100 #
b100 (
b11 "
b11 '
0%
#10000
0$
#15000
b1100 !
b1100 )
1$
#16000
b11000010011110100110011001011000110001000111101001101000010000001100011011110010110001100110001 ,
b1100 +
#20000
0$
#25000
b11000 !
b11000 )
1$
#26000
b11000010011110100110011001011000110001000111101001101000010000001100011011110010110001100110010 ,
b11000 +
#30000
0$
#35000
b100100 !
b100100 )
1$
#36000
1%
b11000010011110100110011001011000110001000111101001101000010000001100011011110010110001100110011 ,
b100100 +
#40000
0$
#45000
b0 !
b0 )
1$
#46000
b1111111111110110 *
b10 #
b10 (
b11111011 "
b11111011 '
0%
b11100100111001101110100 ,
b0 +
#50000
0$
#55000
b11111111111111111111111111110110 !
b11111111111111111111111111110110 )
1$
#56000
b1100001001111010010110100110101001011000110001000111101001100100010000001100011011110010110001100110001 ,
b11111111111111111111111111110110 +
#60000
0$
#65000
b11111111111111111111111111101100 !
b11111111111111111111111111101100 )
1$
#66000
b1100001001111010010110100110101001011000110001000111101001100100010000001100011011110010110001100110010 ,
b11111111111111111111111111101100 +
